petit_python_publipost_connector/__init__.py
petit_python_publipost_connector/datastructure.py
petit_python_publipost_connector/server_provider.py
petit_python_publipost_connector/template_db.py
petit_python_publipost_connector/utils.py
petit_python_publipost_connector/engine/__init__.py
petit_python_publipost_connector/engine/engine.py
petit_python_publipost_connector-0.2.0.dist-info/LICENSE.txt
petit_python_publipost_connector-0.2.0.dist-info/METADATA
petit_python_publipost_connector-0.2.0.dist-info/WHEEL
petit_python_publipost_connector-0.2.0.dist-info/top_level.txt
petit_python_publipost_connector-0.2.0.dist-info/RECORD
