Metadata-Version: 2.1
Name: petit-python-publipost-connector
Version: 0.2.0
Summary: Connect your templates to the petit_publipost gateway
Home-page: https://github.com/Plawn/petit_python_publipost_connector
Author: Plawn
Author-email: plawn.yay@gmail.com
License: apache-2.0
Platform: UNKNOWN
Requires-Python: >=3.8
Requires-Dist: fastapi (==0.68.0)
Requires-Dist: uvicorn (==0.11.8)
Requires-Dist: minio (==7.1.0)
Requires-Dist: python-multipart (==0.0.5)
